batchfetch/__init__.py
batchfetch/batchfetch_base.py
batchfetch/batchfetch_cli.py
batchfetch/batchfetch_git.py
batchfetch/helpers.py
batchfetch-1.3.6.dist-info/licenses/LICENSE
batchfetch-1.3.6.dist-info/METADATA
batchfetch-1.3.6.dist-info/WHEEL
batchfetch-1.3.6.dist-info/entry_points.txt
batchfetch-1.3.6.dist-info/top_level.txt
batchfetch-1.3.6.dist-info/RECORD
