Metadata-Version: 2.4
Name: batchfetch
Version: 1.3.6
Summary: Efficiently clone and pull multiple Git repositories.
Home-page: https://github.com/jamescherti/batchfetch
Author: James Cherti
License: GPLv3
Classifier: Development Status :: 5 - Production/Stable
Classifier: License :: OSI Approved :: GNU General Public License (GPL)
Classifier: License :: OSI Approved :: GNU General Public License v3 (GPLv3)
Classifier: Environment :: Console
Classifier: Operating System :: POSIX :: Linux
Classifier: Operating System :: POSIX :: Other
Classifier: Programming Language :: Python :: 3
Classifier: Topic :: Software Development :: Version Control :: Git
Classifier: Topic :: Utilities
Requires-Python: >=3.6, <4
License-File: LICENSE
Requires-Dist: colorama
Requires-Dist: schema
Requires-Dist: setproctitle
Requires-Dist: PyYAML
Dynamic: author
Dynamic: classifier
Dynamic: description
Dynamic: description-content-type
Dynamic: home-page
Dynamic: license
Dynamic: license-file
Dynamic: requires-dist
Dynamic: requires-python
Dynamic: summary
